tap_clubspeed/__init__.py
tap_clubspeed/clubspeed.py
tap_clubspeed/discover.py
tap_clubspeed/streams.py
tap_clubspeed/sync.py
tap_clubspeed/schemas/booking.json
tap_clubspeed/schemas/booking_availability.json
tap_clubspeed/schemas/check_details.json
tap_clubspeed/schemas/checks.json
tap_clubspeed/schemas/customers.json
tap_clubspeed/schemas/discount_types.json
tap_clubspeed/schemas/event_heat_details.json
tap_clubspeed/schemas/event_heat_types.json
tap_clubspeed/schemas/event_reservation_links.json
tap_clubspeed/schemas/event_reservation_types.json
tap_clubspeed/schemas/event_reservations.json
tap_clubspeed/schemas/event_rounds.json
tap_clubspeed/schemas/event_statuses.json
tap_clubspeed/schemas/event_task_types.json
tap_clubspeed/schemas/event_tasks.json
tap_clubspeed/schemas/event_types.json
tap_clubspeed/schemas/events.json
tap_clubspeed/schemas/gift_card_history.json
tap_clubspeed/schemas/heat_details.json
tap_clubspeed/schemas/heat_main.json
tap_clubspeed/schemas/heat_types.json
tap_clubspeed/schemas/membership_types.json
tap_clubspeed/schemas/memberships.json
tap_clubspeed/schemas/payments.json
tap_clubspeed/schemas/payments_voided.json
tap_clubspeed/schemas/product_classes.json
tap_clubspeed/schemas/products.json
tap_clubspeed/schemas/reservations.json
tap_clubspeed/schemas/schema-fixture.json
tap_clubspeed/schemas/sources.json
tap_clubspeed/schemas/taxes.json
tap_clubspeed/schemas/users.json
tap_clubspeed-0.3.1.dist-info/LICENSE
tap_clubspeed-0.3.1.dist-info/METADATA
tap_clubspeed-0.3.1.dist-info/WHEEL
tap_clubspeed-0.3.1.dist-info/entry_points.txt
tap_clubspeed-0.3.1.dist-info/top_level.txt
tap_clubspeed-0.3.1.dist-info/RECORD
