Metadata-Version: 2.1
Name: tap-clubspeed
Version: 0.3.1
Summary: Singer.io tap for extracting data from the Clubspeed API
Home-page: https://andyjiang.com
Author: lambtron
Author-email: andyjiang@gmail.com
License: UNKNOWN
Platform: UNKNOWN
Classifier: Programming Language :: Python :: 3 :: Only
Requires-Dist: singer-python (==5.1.5)
Requires-Dist: requests (==2.19.1)
